aamt/__init__.py
aamt/cli.py
aamt/config.py
aamt/fixture.py
aamt/plugin.py
aamt/sample.py
aamt/scaffold.py
aamt-0.2.5.dist-info/entry_points.txt
aamt-0.2.5.dist-info/METADATA
aamt-0.2.5.dist-info/WHEEL
aamt-0.2.5.dist-info/RECORD
